scnetwork/__init__.py
scnetwork/scnetwork.py
scnetwork-1.1.3.dist-info/LICENSE.txt
scnetwork-1.1.3.dist-info/METADATA
scnetwork-1.1.3.dist-info/WHEEL
scnetwork-1.1.3.dist-info/top_level.txt
scnetwork-1.1.3.dist-info/RECORD
