Metadata-Version: 2.2
Name: scnetwork
Version: 1.1.3
Home-page: https://github.com/sapiens-technology/SCNet
Author: SAPIENS TECHNOLOGY
License: Proprietary Software
License-File: LICENSE.txt
Requires-Dist: torch
Requires-Dist: tiktoken
Requires-Dist: numpy
Requires-Dist: ijson
Requires-Dist: psutil
Requires-Dist: semantic-comparison-network
Requires-Dist: hurnet
Requires-Dist: requests
Requires-Dist: tqdm
Dynamic: author
Dynamic: home-page
Dynamic: license
Dynamic: requires-dist
